LICENSE
README.md
doltcli_ex/__init__.py
doltcli_ex/io.py
doltcli_ex/operate.py
doltcli_ex/scripts/add.py
doltcli_ex/scripts/rm.py
doltcli_ex-0.1.14.dist-info/entry_points.txt
doltcli_ex-0.1.14.dist-info/LICENSE
doltcli_ex-0.1.14.dist-info/WHEEL
doltcli_ex-0.1.14.dist-info/METADATA
doltcli_ex-0.1.14.dist-info/RECORD
